quadra/__init__.py
quadra/callbacks/__init__.py
quadra/callbacks/anomalib.py
quadra/callbacks/lightning.py
quadra/callbacks/mlflow.py
quadra/callbacks/scheduler.py
quadra/configs/__init__.py
quadra/configs/backbone/caformer_m36.yaml
quadra/configs/backbone/caformer_s36.yaml
quadra/configs/backbone/convnextv2_base.yaml
quadra/configs/backbone/convnextv2_femto.yaml
quadra/configs/backbone/convnextv2_tiny.yaml
quadra/configs/backbone/dino_vitb8.yaml
quadra/configs/backbone/dino_vits8.yaml
quadra/configs/backbone/dinov2_vitb14.yaml
quadra/configs/backbone/dinov2_vits14.yaml
quadra/configs/backbone/efficientnet_b0.yaml
quadra/configs/backbone/efficientnet_b1.yaml
quadra/configs/backbone/efficientnet_b2.yaml
quadra/configs/backbone/efficientnet_b3.yaml
quadra/configs/backbone/efficientnetv2_s.yaml
quadra/configs/backbone/levit_128s.yaml
quadra/configs/backbone/mnasnet0_5.yaml
quadra/configs/backbone/resnet101.yaml
quadra/configs/backbone/resnet18.yaml
quadra/configs/backbone/resnet18_ssl.yaml
quadra/configs/backbone/resnet50.yaml
quadra/configs/backbone/smp.yaml
quadra/configs/backbone/tiny_vit_21m_224.yaml
quadra/configs/backbone/unetr.yaml
quadra/configs/backbone/vit16_base.yaml
quadra/configs/backbone/vit16_small.yaml
quadra/configs/backbone/vit16_tiny.yaml
quadra/configs/backbone/xcit_tiny_24_p8_224.yaml
quadra/configs/callbacks/all.yaml
quadra/configs/callbacks/default.yaml
quadra/configs/callbacks/default_anomalib.yaml
quadra/configs/config.yaml
quadra/configs/core/default.yaml
quadra/configs/datamodule/base/anomaly.yaml
quadra/configs/datamodule/base/classification.yaml
quadra/configs/datamodule/base/multilabel_classification.yaml
quadra/configs/datamodule/base/segmentation.yaml
quadra/configs/datamodule/base/segmentation_multiclass.yaml
quadra/configs/datamodule/base/sklearn_classification.yaml
quadra/configs/datamodule/base/sklearn_classification_patch.yaml
quadra/configs/datamodule/base/ssl.yaml
quadra-2.6.2.dist-info/METADATA
quadra-2.6.2.dist-info/WHEEL
quadra-2.6.2.dist-info/entry_points.txt
quadra-2.6.2.dist-info/licenses/LICENSE
quadra-2.6.2.dist-info/RECORD
