Metadata-Version: 2.4
Name: quadra
Version: 2.6.2
Summary: Deep Learning experiment orchestration library
License: Apache-2.0
License-File: LICENSE
Keywords: deep learning,experiment,lightning,hydra-core
Author: Federico Belotti
Author-email: federico.belotti@orobix.com
Requires-Python: >=3.10,<3.11
Classifier: Intended Audience :: Developers
Classifier: Intended Audience :: Education
Classifier: Intended Audience :: Science/Research
Classifier: License :: OSI Approved :: Apache Software License
Classifier: Programming Language :: Python :: 3
Classifier: Programming Language :: Python :: 3.10
Classifier: Topic :: Scientific/Engineering :: Artificial Intelligence
Classifier: Topic :: Software Development
Classifier: Topic :: Software Development :: Libraries
Classifier: Topic :: Software Development :: Libraries :: Python Modules
Provides-Extra: onnx
Requires-Dist: albumentations (>=1.3,<1.4)
Requires-Dist: anomalib-orobix (==0.7.0.dev150)
Requires-Dist: boto3 (>=1.26,<1.27)
Requires-Dist: grad-cam-orobix (==1.5.3.dev1)
Requires-Dist: h5py (>=3.8,<3.9)
Requires-Dist: hydra_colorlog (>=1.2,<1.3)
Requires-Dist: hydra_core (>=1.3,<1.4)
Requires-Dist: hydra_optuna_sweeper (>=1.2,<1.3)
Requires-Dist: label_studio_converter (>=0.0,<0.1)
Requires-Dist: matplotlib (>=3.6,<3.7)
Requires-Dist: minio (>=7.1,<7.2)
Requires-Dist: mlflow-skinny (>=2.3.1,<3.0.0)
Requires-Dist: numpy (<2)
Requires-Dist: nvitop (>=0.11,<0.12)
Requires-Dist: onnx (==1.15.0) ; extra == "onnx"
Requires-Dist: onnxconverter-common (>=1.14.0,<2.0.0) ; extra == "onnx"
Requires-Dist: onnxruntime_gpu (==1.23.2) ; extra == "onnx"
Requires-Dist: onnxsim (==0.4.28) ; extra == "onnx"
Requires-Dist: opencv_python_headless (>=4.7.0,<4.8.0)
Requires-Dist: pandas (<2.0)
Requires-Dist: pillow (>=10,<11)
Requires-Dist: pydantic (>=1.10.10)
Requires-Dist: python_dotenv (>=0.21,<0.22)
Requires-Dist: pytorch_lightning (>=2.4,<2.5)
Requires-Dist: rich (>=13.2,<13.3)
Requires-Dist: scikit_learn (>=1.6,<1.7)
Requires-Dist: scikit_multilearn (>=0.2,<0.3)
Requires-Dist: seaborn (>=0.12,<0.13)
Requires-Dist: segmentation_models_pytorch-orobix (==0.3.3.dev1)
Requires-Dist: tensorboard (>=2.11,<2.12)
Requires-Dist: timm (==0.9.12)
Requires-Dist: torch (==2.8.0)
Requires-Dist: torchinfo (>=1.8,<1.9)
Requires-Dist: torchmetrics (>=0.10,<0.11)
Requires-Dist: torchsummary (>=1.5,<1.6)
Requires-Dist: torchvision (==0.23)
Requires-Dist: tripy (>=1.0,<1.1)
Requires-Dist: typing_extensions (==4.11.0) ; python_version < "3.10"
Requires-Dist: xxhash (>=3.2,<3.3)
Project-URL: Homepage, https://orobix.github.io/quadra
Project-URL: Repository, https://github.com/orobix/quadra
